{
  "version": "6.5.0",
  "objects": [
    {
      "id": "2cf5c260-2ce4-11e9-81a3-0f5bd8b0a7ac",
      "type": "visualization",
      "updated_at": "2019-03-14T18:13:15.408Z",
      "version": 4,
      "attributes": {
        "title": "Embarkation Port for Cases",
        "visState": "{\"title\":\"Embarkation Port for Cases\",\"type\":\"tile_map\",\"params\":{\"addTooltip\":true,\"colorSchema\":\"Yellow to Red\",\"heatClusterSize\":1.5,\"isDesaturated\":true,\"legendPosition\":\"bottomright\",\"mapCenter\":[0,0],\"mapType\":\"Scaled Circle Markers\",\"mapZoom\":2,\"wms\":{\"enabled\":false,\"options\":{\"format\":\"image/png\",\"transparent\":true},\"selectedTmsLayer\":{\"attribution\":\"<p>&#169; <a href=\\\"http://www.openstreetmap.org/copyright\\\">OpenStreetMap</a> contributors | <a href=\\\"https://www.elastic.co/elastic-maps-service\\\">Elastic Maps Service</a></p>&#10;\",\"id\":\"road_map\",\"maxZoom\":18,\"minZoom\":0,\"subdomains\":[],\"url\":\"https://tiles.maps.elastic.co/v2/default/{z}/{x}/{y}.png?elastic_tile_service_tos=agree&my_app_name=kibana&my_app_version=6.5.0&license=33bdd25d-6a8e-479c-a618-4ee0b1c82b52\"}}},\"aggs\":[{\"id\":\"1\",\"enabled\":true,\"type\":\"count\",\"schema\":\"metric\",\"params\":{}},{\"id\":\"2\",\"enabled\":true,\"type\":\"geohash_grid\",\"schema\":\"segment\",\"params\":{\"field\":\"passenger.embarkation_coordination\",\"autoPrecision\":true,\"isFilteredByCollar\":true,\"useGeocentroid\":true,\"mapZoom\":2,\"mapCenter\":{\"lon\":12.304687500000002,\"lat\":41.77131167976407},\"precision\":7}}]}",
        "uiStateJSON": "{\"mapCenter\":[41.64007838467894,12.304687500000002],\"mapZoom\":2}",
        "description": "",
        "version": 1,
        "kibanaSavedObjectMeta": {
          "searchSourceJSON": "{\"index\":\"dcb454f0-2c12-11e9-81a3-0f5bd8b0a7ac\",\"query\":{\"language\":\"lucene\",\"query\":\"\"},\"filter\":[]}"
        }
      }
    },
    {
      "id": "20062130-2ee2-11e9-b8b9-8b6cf228ac97",
      "type": "visualization",
      "updated_at": "2019-03-14T18:04:10.429Z",
      "version": 7,
      "attributes": {
        "title": "[FlightPax] Inbound Flights",
        "visState": "{\"title\":\"[FlightPax] Inbound Flights\",\"type\":\"metric\",\"params\":{\"addLegend\":false,\"addTooltip\":true,\"metric\":{\"colorSchema\":\"Green to Red\",\"colorsRange\":[{\"from\":0,\"to\":10000}],\"invertColors\":false,\"labels\":{\"show\":false},\"metricColorMode\":\"None\",\"percentageMode\":false,\"style\":{\"bgColor\":false,\"bgFill\":\"#000\",\"fontSize\":30,\"labelColor\":false,\"subText\":\"\"},\"useRanges\":false},\"type\":\"metric\"},\"aggs\":[{\"id\":\"1\",\"enabled\":true,\"type\":\"cardinality\",\"schema\":\"metric\",\"params\":{\"field\":\"flightNumber.keyword\",\"customLabel\":\"\"}}]}",
        "uiStateJSON": "{}",
        "description": "",
        "version": 1,
        "kibanaSavedObjectMeta": {
          "searchSourceJSON": "{\"index\":\"96df0890-2ba8-11e9-a5e4-2bbcf61c6cb1\",\"query\":{\"language\":\"kuery\",\"query\":\"eta <= now+3d and eta >= now and direction.keyword : I\"},\"filter\":[]}"
        }
      }
    },
    {
      "id": "8e6b8b10-2ee2-11e9-b8b9-8b6cf228ac97",
      "type": "visualization",
      "updated_at": "2019-03-14T18:04:10.426Z",
      "version": 7,
      "attributes": {
        "title": "[FlightPax] Outbound Flights",
        "visState": "{\"title\":\"[FlightPax] Outbound Flights\",\"type\":\"metric\",\"params\":{\"addLegend\":false,\"addTooltip\":true,\"metric\":{\"colorSchema\":\"Green to Red\",\"colorsRange\":[{\"from\":0,\"to\":10000}],\"invertColors\":false,\"labels\":{\"show\":false},\"metricColorMode\":\"None\",\"percentageMode\":false,\"style\":{\"bgColor\":false,\"bgFill\":\"#000\",\"fontSize\":30,\"labelColor\":false,\"subText\":\"\"},\"useRanges\":false},\"type\":\"metric\"},\"aggs\":[{\"id\":\"1\",\"enabled\":true,\"type\":\"cardinality\",\"schema\":\"metric\",\"params\":{\"field\":\"flightNumber.keyword\",\"customLabel\":\"Outbound Flights\"}}]}",
        "uiStateJSON": "{}",
        "description": "",
        "version": 1,
        "kibanaSavedObjectMeta": {
          "searchSourceJSON": "{\"index\":\"96df0890-2ba8-11e9-a5e4-2bbcf61c6cb1\",\"query\":{\"query\":\"eta <= now+3d and eta >= now and direction.keyword : O\",\"language\":\"kuery\"},\"filter\":[]}"
        }
      }
    },
    {
      "id": "881e1000-2ee9-11e9-b8b9-8b6cf228ac97",
      "type": "visualization",
      "updated_at": "2019-03-14T18:04:10.424Z",
      "version": 7,
      "attributes": {
        "title": "[FlightPax] Outbound Passengers",
        "visState": "{\"title\":\"[FlightPax] Outbound Passengers\",\"type\":\"metric\",\"params\":{\"addLegend\":false,\"addTooltip\":true,\"metric\":{\"colorSchema\":\"Green to Red\",\"colorsRange\":[{\"from\":0,\"to\":10000}],\"invertColors\":false,\"labels\":{\"show\":false},\"metricColorMode\":\"None\",\"percentageMode\":false,\"style\":{\"bgColor\":false,\"bgFill\":\"#000\",\"fontSize\":30,\"labelColor\":false,\"subText\":\"\"},\"useRanges\":false},\"type\":\"metric\"},\"aggs\":[{\"id\":\"1\",\"enabled\":true,\"type\":\"cardinality\",\"schema\":\"metric\",\"params\":{\"field\":\"passengerId\",\"customLabel\":\"Outbound Passengers\"}}]}",
        "uiStateJSON": "{}",
        "description": "",
        "version": 1,
        "kibanaSavedObjectMeta": {
          "searchSourceJSON": "{\"index\":\"96df0890-2ba8-11e9-a5e4-2bbcf61c6cb1\",\"query\":{\"query\":\"eta <= now+3d and eta >= now and direction.keyword : O\",\"language\":\"kuery\"},\"filter\":[]}"
        }
      }
    },
    {
      "id": "846e0ae0-2eea-11e9-b8b9-8b6cf228ac97",
      "type": "visualization",
      "updated_at": "2019-03-14T18:04:11.567Z",
      "version": 5,
      "attributes": {
        "title": "[FlightPax] Inbound Passengers",
        "visState": "{\"title\":\"[FlightPax] Inbound Passengers\",\"type\":\"metric\",\"params\":{\"addLegend\":false,\"addTooltip\":true,\"metric\":{\"colorSchema\":\"Green to Red\",\"colorsRange\":[{\"from\":0,\"to\":10000}],\"invertColors\":false,\"labels\":{\"show\":false},\"metricColorMode\":\"None\",\"percentageMode\":false,\"style\":{\"bgColor\":false,\"bgFill\":\"#000\",\"fontSize\":30,\"labelColor\":false,\"subText\":\"\"},\"useRanges\":false},\"type\":\"metric\"},\"aggs\":[{\"id\":\"1\",\"enabled\":true,\"type\":\"cardinality\",\"schema\":\"metric\",\"params\":{\"field\":\"passengerId\",\"customLabel\":\"Inbound Passengers\"}}]}",
        "uiStateJSON": "{}",
        "description": "",
        "version": 1,
        "kibanaSavedObjectMeta": {
          "searchSourceJSON": "{\"index\":\"96df0890-2ba8-11e9-a5e4-2bbcf61c6cb1\",\"query\":{\"query\":\"eta <= now+3d and eta >= now and direction.keyword : I\",\"language\":\"kuery\"},\"filter\":[]}"
        }
      }
    },
    {
      "id": "cd0264d0-3094-11e9-b8b9-8b6cf228ac97",
      "type": "visualization",
      "updated_at": "2019-03-14T18:04:10.421Z",
      "version": 7,
      "attributes": {
        "title": "Case Status",
        "visState": "{\"title\":\"Case Status\",\"type\":\"pie\",\"params\":{\"addLegend\":true,\"addTooltip\":true,\"isDonut\":true,\"labels\":{\"last_level\":true,\"show\":true,\"truncate\":90,\"values\":true},\"legendPosition\":\"right\",\"type\":\"pie\"},\"aggs\":[{\"id\":\"1\",\"enabled\":true,\"type\":\"count\",\"schema\":\"metric\",\"params\":{\"customLabel\":\"Status\"}},{\"id\":\"2\",\"enabled\":true,\"type\":\"terms\",\"schema\":\"segment\",\"params\":{\"field\":\"status.keyword\",\"size\":5,\"order\":\"desc\",\"orderBy\":\"1\",\"otherBucket\":false,\"otherBucketLabel\":\"Other\",\"missingBucket\":false,\"missingBucketLabel\":\"Missing\",\"customLabel\":\"Case Status\"}}]}",
        "uiStateJSON": "{\"vis\":{\"legendOpen\":false}}",
        "description": "",
        "version": 1,
        "kibanaSavedObjectMeta": {
          "searchSourceJSON": "{\"index\":\"dcb454f0-2c12-11e9-81a3-0f5bd8b0a7ac\",\"query\":{\"language\":\"kuery\",\"query\":\"\"},\"filter\":[]}"
        }
      }
    },
    {
      "id": "08af9740-3a0a-11e9-95bb-75d44e71a49d",
      "type": "visualization",
      "updated_at": "2019-03-14T18:04:11.563Z",
      "version": 2,
      "attributes": {
        "title": "Passenger Count by Passport Issuing Country",
        "visState": "{\"title\":\"Passenger Count by Passport Issuing Country\",\"type\":\"histogram\",\"params\":{\"type\":\"histogram\",\"grid\":{\"categoryLines\":false,\"style\":{\"color\":\"#eee\"}},\"categoryAxes\":[{\"id\":\"CategoryAxis-1\",\"type\":\"category\",\"position\":\"bottom\",\"show\":true,\"style\":{},\"scale\":{\"type\":\"linear\"},\"labels\":{\"show\":true,\"truncate\":100},\"title\":{}}],\"valueAxes\":[{\"id\":\"ValueAxis-1\",\"name\":\"LeftAxis-1\",\"type\":\"value\",\"position\":\"left\",\"show\":true,\"style\":{},\"scale\":{\"type\":\"linear\",\"mode\":\"normal\"},\"labels\":{\"show\":true,\"rotate\":0,\"filter\":false,\"truncate\":100},\"title\":{\"text\":\"Count\"}}],\"seriesParams\":[{\"show\":\"true\",\"type\":\"histogram\",\"mode\":\"stacked\",\"data\":{\"label\":\"Count\",\"id\":\"1\"},\"valueAxis\":\"ValueAxis-1\",\"drawLinesBetweenPoints\":true,\"showCircles\":true}],\"addTooltip\":true,\"addLegend\":true,\"legendPosition\":\"right\",\"times\":[],\"addTimeMarker\":false},\"aggs\":[{\"id\":\"1\",\"enabled\":true,\"type\":\"count\",\"schema\":\"metric\",\"params\":{}},{\"id\":\"2\",\"enabled\":true,\"type\":\"terms\",\"schema\":\"segment\",\"params\":{\"field\":\"documents.issuanceCountry.keyword\",\"size\":40,\"order\":\"desc\",\"orderBy\":\"1\",\"otherBucket\":false,\"otherBucketLabel\":\"Other\",\"missingBucket\":false,\"missingBucketLabel\":\"Missing\"}}]}",
        "uiStateJSON": "{\"vis\":{\"legendOpen\":false}}",
        "description": "",
        "version": 1,
        "kibanaSavedObjectMeta": {
          "searchSourceJSON": "{\"index\":\"96df0890-2ba8-11e9-a5e4-2bbcf61c6cb1\",\"query\":{\"query\":\"\",\"language\":\"lucene\"},\"filter\":[]}"
        }
      }
    },
    {
      "id": "938c2f80-3a0b-11e9-95bb-75d44e71a49d",
      "type": "visualization",
      "updated_at": "2019-03-14T18:04:10.417Z",
      "version": 2,
      "attributes": {
        "title": "ruleHitAudit",
        "visState": "{\"title\":\"ruleHitAudit\",\"type\":\"table\",\"params\":{\"perPage\":10,\"showPartialRows\":false,\"showMetricsAtAllLevels\":false,\"sort\":{\"columnIndex\":null,\"direction\":null},\"showTotal\":false,\"totalFunc\":\"sum\"},\"aggs\":[{\"id\":\"1\",\"enabled\":true,\"type\":\"count\",\"schema\":\"metric\",\"params\":{}},{\"id\":\"2\",\"enabled\":true,\"type\":\"terms\",\"schema\":\"bucket\",\"params\":{\"field\":\"hit_summary.hit_detail.description.keyword\",\"size\":5,\"order\":\"desc\",\"orderBy\":\"1\",\"otherBucket\":false,\"otherBucketLabel\":\"Other\",\"missingBucket\":true,\"missingBucketLabel\":\"Missing\"}},{\"id\":\"3\",\"enabled\":true,\"type\":\"terms\",\"schema\":\"bucket\",\"params\":{\"field\":\"hit_disposition.valid.keyword\",\"size\":5,\"order\":\"desc\",\"orderBy\":\"1\",\"otherBucket\":false,\"otherBucketLabel\":\"Other\",\"missingBucket\":true,\"missingBucketLabel\":\"Missing\"}}]}",
        "uiStateJSON": "{\"vis\":{\"params\":{\"sort\":{\"columnIndex\":null,\"direction\":null}}}}",
        "description": "",
        "version": 1,
        "kibanaSavedObjectMeta": {
          "searchSourceJSON": "{\"index\":\"dcb454f0-2c12-11e9-81a3-0f5bd8b0a7ac\",\"query\":{\"query\":\"\",\"language\":\"lucene\"},\"filter\":[]}"
        }
      }
    },
    {
      "id": "dcb454f0-2c12-11e9-81a3-0f5bd8b0a7ac",
      "type": "index-pattern",
      "updated_at": "2019-02-10T03:22:41.755Z",
      "version": 4,
      "attributes": {
        "title": "case*",
        "timeFieldName": "flight.flight_date",
        "fields": "[{\"name\":\"@timestamp\",\"type\":\"date\",\"count\":0,\"scripted\":false,\"searchable\":true,\"aggregatable\":true,\"readFromDocValues\":true},{\"name\":\"@version\",\"type\":\"string\",\"count\":0,\"scripted\":false,\"searchable\":true,\"aggregatable\":false,\"readFromDocValues\":false},{\"name\":\"@version.keyword\",\"type\":\"string\",\"count\":0,\"scripted\":false,\"searchable\":true,\"aggregatable\":true,\"readFromDocValues\":true},{\"name\":\"_id\",\"type\":\"string\",\"count\":0,\"scripted\":false,\"searchable\":true,\"aggregatable\":true,\"readFromDocValues\":false},{\"name\":\"_index\",\"type\":\"string\",\"count\":0,\"scripted\":false,\"searchable\":true,\"aggregatable\":true,\"readFromDocValues\":false},{\"name\":\"_score\",\"type\":\"number\",\"count\":0,\"scripted\":false,\"searchable\":false,\"aggregatable\":false,\"readFromDocValues\":false},{\"name\":\"_source\",\"type\":\"_source\",\"count\":0,\"scripted\":false,\"searchable\":false,\"aggregatable\":false,\"readFromDocValues\":false},{\"name\":\"_type\",\"type\":\"string\",\"count\":0,\"scripted\":false,\"searchable\":true,\"aggregatable\":true,\"readFromDocValues\":false},{\"name\":\"citizenshipcountry\",\"type\":\"string\",\"count\":0,\"scripted\":false,\"searchable\":true,\"aggregatable\":false,\"readFromDocValues\":false},{\"name\":\"citizenshipcountry.keyword\",\"type\":\"string\",\"count\":0,\"scripted\":false,\"searchable\":true,\"aggregatable\":true,\"readFromDocValues\":true},{\"name\":\"created_at\",\"type\":\"date\",\"count\":0,\"scripted\":false,\"searchable\":true,\"aggregatable\":true,\"readFromDocValues\":true},{\"name\":\"disposition\",\"type\":\"string\",\"count\":0,\"scripted\":false,\"searchable\":true,\"aggregatable\":false,\"readFromDocValues\":false},{\"name\":\"dob\",\"type\":\"date\",\"count\":0,\"scripted\":false,\"searchable\":true,\"aggregatable\":true,\"readFromDocValues\":true},{\"name\":\"document\",\"type\":\"string\",\"count\":0,\"scripted\":false,\"searchable\":true,\"aggregatable\":false,\"readFromDocValues\":false},{\"name\":\"document.keyword\",\"type\":\"string\",\"count\":0,\"scripted\":false,\"searchable\":true,\"aggregatable\":true,\"readFromDocValues\":true},{\"name\":\"firstName\",\"type\":\"string\",\"count\":0,\"scripted\":false,\"searchable\":true,\"aggregatable\":false,\"readFromDocValues\":false},{\"name\":\"firstName.keyword\",\"type\":\"string\",\"count\":0,\"scripted\":false,\"searchable\":true,\"aggregatable\":true,\"readFromDocValues\":true},{\"name\":\"firstname\",\"type\":\"string\",\"count\":0,\"scripted\":false,\"searchable\":true,\"aggregatable\":false,\"readFromDocValues\":false},{\"name\":\"firstname.keyword\",\"type\":\"string\",\"count\":0,\"scripted\":false,\"searchable\":true,\"aggregatable\":true,\"readFromDocValues\":true},{\"name\":\"flight.eta\",\"type\":\"date\",\"count\":0,\"scripted\":false,\"searchable\":true,\"aggregatable\":true,\"readFromDocValues\":true},{\"name\":\"flight.eta_date\",\"type\":\"date\",\"count\":0,\"scripted\":false,\"searchable\":true,\"aggregatable\":true,\"readFromDocValues\":true},{\"name\":\"flight.etd\",\"type\":\"date\",\"count\":0,\"scripted\":false,\"searchable\":true,\"aggregatable\":true,\"readFromDocValues\":true},{\"name\":\"flight.etd_date\",\"type\":\"date\",\"count\":0,\"scripted\":false,\"searchable\":true,\"aggregatable\":true,\"readFromDocValues\":true},{\"name\":\"flight.flight_date\",\"type\":\"date\",\"count\":0,\"scripted\":false,\"searchable\":true,\"aggregatable\":true,\"readFromDocValues\":true},{\"name\":\"flight.flight_number\",\"type\":\"string\",\"count\":0,\"scripted\":false,\"searchable\":true,\"aggregatable\":false,\"readFromDocValues\":false},{\"name\":\"flight.flight_number.keyword\",\"type\":\"string\",\"count\":0,\"scripted\":false,\"searchable\":true,\"aggregatable\":true,\"readFromDocValues\":true},{\"name\":\"flight.full_flight_number\",\"type\":\"string\",\"count\":0,\"scripted\":false,\"searchable\":true,\"aggregatable\":false,\"readFromDocValues\":false},{\"name\":\"flight.full_flight_number.keyword\",\"type\":\"string\",\"count\":0,\"scripted\":false,\"searchable\":true,\"aggregatable\":true,\"readFromDocValues\":true},{\"name\":\"flight.id\",\"type\":\"number\",\"count\":0,\"scripted\":false,\"searchable\":true,\"aggregatable\":true,\"readFromDocValues\":true},{\"name\":\"flight.origin\",\"type\":\"string\",\"count\":0,\"scripted\":false,\"searchable\":true,\"aggregatable\":false,\"readFromDocValues\":false},{\"name\":\"flight.origin.keyword\",\"type\":\"string\",\"count\":0,\"scripted\":false,\"searchable\":true,\"aggregatable\":true,\"readFromDocValues\":true},{\"name\":\"flight.origin_country\",\"type\":\"string\",\"count\":0,\"scripted\":false,\"searchable\":true,\"aggregatable\":false,\"readFromDocValues\":false},{\"name\":\"flight.origin_country.keyword\",\"type\":\"string\",\"count\":0,\"scripted\":false,\"searchable\":true,\"aggregatable\":true,\"readFromDocValues\":true},{\"name\":\"flight.passenger_count\",\"type\":\"number\",\"count\":0,\"scripted\":false,\"searchable\":true,\"aggregatable\":true,\"readFromDocValues\":true},{\"name\":\"flight.rule_hit_count\",\"type\":\"number\",\"count\":0,\"scripted\":false,\"searchable\":true,\"aggregatable\":true,\"readFromDocValues\":true},{\"name\":\"flightId\",\"type\":\"number\",\"count\":0,\"scripted\":false,\"searchable\":true,\"aggregatable\":true,\"readFromDocValues\":true},{\"name\":\"flightNumber\",\"type\":\"string\",\"count\":0,\"scripted\":false,\"searchable\":true,\"aggregatable\":false,\"readFromDocValues\":false},{\"name\":\"flightNumber.keyword\",\"type\":\"string\",\"count\":0,\"scripted\":false,\"searchable\":true,\"aggregatable\":true,\"readFromDocValues\":true},{\"name\":\"flightid\",\"type\":\"number\",\"count\":0,\"scripted\":false,\"searchable\":true,\"aggregatable\":true,\"readFromDocValues\":true},{\"name\":\"flightnumber\",\"type\":\"string\",\"count\":0,\"scripted\":false,\"searchable\":true,\"aggregatable\":false,\"readFromDocValues\":false},{\"name\":\"flightnumber.keyword\",\"type\":\"string\",\"count\":0,\"scripted\":false,\"searchable\":true,\"aggregatable\":true,\"readFromDocValues\":true},{\"name\":\"highPriorityRuleCatId\",\"type\":\"number\",\"count\":0,\"scripted\":false,\"searchable\":true,\"aggregatable\":true,\"readFromDocValues\":true},{\"name\":\"highpriorityrulecatid\",\"type\":\"number\",\"count\":0,\"scripted\":false,\"searchable\":true,\"aggregatable\":true,\"readFromDocValues\":true},{\"name\":\"hit_disposition.comments.comment\",\"type\":\"string\",\"count\":0,\"scripted\":false,\"searchable\":true,\"aggregatable\":false,\"readFromDocValues\":false},{\"name\":\"hit_disposition.comments.comment.keyword\",\"type\":\"string\",\"count\":0,\"scripted\":false,\"searchable\":true,\"aggregatable\":true,\"readFromDocValues\":true},{\"name\":\"hit_disposition.comments.comments\",\"type\":\"string\",\"count\":0,\"scripted\":false,\"searchable\":true,\"aggregatable\":false,\"readFromDocValues\":false},{\"name\":\"hit_disposition.comments.comments.keyword\",\"type\":\"string\",\"count\":0,\"scripted\":false,\"searchable\":true,\"aggregatable\":true,\"readFromDocValues\":true},{\"name\":\"hit_disposition.comments.created_at\",\"type\":\"date\",\"count\":0,\"scripted\":false,\"searchable\":true,\"aggregatable\":true,\"readFromDocValues\":true},{\"name\":\"hit_disposition.comments.created_by\",\"type\":\"string\",\"count\":0,\"scripted\":false,\"searchable\":true,\"aggregatable\":false,\"readFromDocValues\":false},{\"name\":\"hit_disposition.comments.created_by.keyword\",\"type\":\"string\",\"count\":0,\"scripted\":false,\"searchable\":true,\"aggregatable\":true,\"readFromDocValues\":true},{\"name\":\"hit_disposition.comments.hit_disp_id\",\"type\":\"number\",\"count\":0,\"scripted\":false,\"searchable\":true,\"aggregatable\":true,\"readFromDocValues\":true},{\"name\":\"hit_disposition.comments.hit_id\",\"type\":\"number\",\"count\":0,\"scripted\":false,\"searchable\":true,\"aggregatable\":true,\"readFromDocValues\":true},{\"name\":\"hit_disposition.comments.id\",\"type\":\"number\",\"count\":0,\"scripted\":false,\"searchable\":true,\"aggregatable\":true,\"readFromDocValues\":true},{\"name\":\"hit_disposition.comments.updated_at\",\"type\":\"date\",\"count\":0,\"scripted\":false,\"searchable\":true,\"aggregatable\":true,\"readFromDocValues\":true},{\"name\":\"hit_disposition.comments.updated_by\",\"type\":\"string\",\"count\":0,\"scripted\":false,\"searchable\":true,\"aggregatable\":false,\"readFromDocValues\":false},{\"name\":\"hit_disposition.comments.updated_by.keyword\",\"type\":\"string\",\"count\":0,\"scripted\":false,\"searchable\":true,\"aggregatable\":true,\"readFromDocValues\":true},{\"name\":\"hit_disposition.created_at\",\"type\":\"date\",\"count\":0,\"scripted\":false,\"searchable\":true,\"aggregatable\":true,\"readFromDocValues\":true},{\"name\":\"hit_disposition.description\",\"type\":\"string\",\"count\":0,\"scripted\":false,\"searchable\":true,\"aggregatable\":false,\"readFromDocValues\":false},{\"name\":\"hit_disposition.description.keyword\",\"type\":\"string\",\"count\":0,\"scripted\":false,\"searchable\":true,\"aggregatable\":true,\"readFromDocValues\":true},{\"name\":\"hit_disposition.hit_id\",\"type\":\"number\",\"count\":0,\"scripted\":false,\"searchable\":true,\"aggregatable\":true,\"readFromDocValues\":true},{\"name\":\"hit_disposition.id\",\"type\":\"number\",\"count\":0,\"scripted\":false,\"searchable\":true,\"aggregatable\":true,\"readFromDocValues\":true},{\"name\":\"hit_disposition.rule_cat_id\",\"type\":\"number\",\"count\":0,\"scripted\":false,\"searchable\":true,\"aggregatable\":true,\"readFromDocValues\":true},{\"name\":\"hit_disposition.status\",\"type\":\"string\",\"count\":0,\"scripted\":false,\"searchable\":true,\"aggregatable\":false,\"readFromDocValues\":false},{\"name\":\"hit_disposition.status.keyword\",\"type\":\"string\",\"count\":0,\"scripted\":false,\"searchable\":true,\"aggregatable\":true,\"readFromDocValues\":true},{\"name\":\"hit_disposition.updated_at\",\"type\":\"date\",\"count\":0,\"scripted\":false,\"searchable\":true,\"aggregatable\":true,\"readFromDocValues\":true},{\"name\":\"hit_disposition.updated_by\",\"type\":\"string\",\"count\":0,\"scripted\":false,\"searchable\":true,\"aggregatable\":false,\"readFromDocValues\":false},{\"name\":\"hit_disposition.updated_by.keyword\",\"type\":\"string\",\"count\":0,\"scripted\":false,\"searchable\":true,\"aggregatable\":true,\"readFromDocValues\":true},{\"name\":\"hit_disposition.valid\",\"type\":\"string\",\"count\":0,\"scripted\":false,\"searchable\":true,\"aggregatable\":false,\"readFromDocValues\":false},{\"name\":\"hit_disposition.valid.keyword\",\"type\":\"string\",\"count\":0,\"scripted\":false,\"searchable\":true,\"aggregatable\":true,\"readFromDocValues\":true},{\"name\":\"hit_summary.created_date\",\"type\":\"date\",\"count\":0,\"scripted\":false,\"searchable\":true,\"aggregatable\":true,\"readFromDocValues\":true},{\"name\":\"hit_summary.flight_id\",\"type\":\"number\",\"count\":0,\"scripted\":false,\"searchable\":true,\"aggregatable\":true,\"readFromDocValues\":true},{\"name\":\"hit_summary.hit_detail.cond_text\",\"type\":\"string\",\"count\":0,\"scripted\":false,\"searchable\":true,\"aggregatable\":false,\"readFromDocValues\":false},{\"name\":\"hit_summary.hit_detail.cond_text.keyword\",\"type\":\"string\",\"count\":0,\"scripted\":false,\"searchable\":true,\"aggregatable\":true,\"readFromDocValues\":true},{\"name\":\"hit_summary.hit_detail.created_date\",\"type\":\"date\",\"count\":0,\"scripted\":false,\"searchable\":true,\"aggregatable\":true,\"readFromDocValues\":true},{\"name\":\"hit_summary.hit_detail.description\",\"type\":\"string\",\"count\":0,\"scripted\":false,\"searchable\":true,\"aggregatable\":false,\"readFromDocValues\":false},{\"name\":\"hit_summary.hit_detail.description.keyword\",\"type\":\"string\",\"count\":0,\"scripted\":false,\"searchable\":true,\"aggregatable\":true,\"readFromDocValues\":true},{\"name\":\"hit_summary.hit_detail.hit_type\",\"type\":\"string\",\"count\":0,\"scripted\":false,\"searchable\":true,\"aggregatable\":false,\"readFromDocValues\":false},{\"name\":\"hit_summary.hit_detail.hit_type.keyword\",\"type\":\"string\",\"count\":0,\"scripted\":false,\"searchable\":true,\"aggregatable\":true,\"readFromDocValues\":true},{\"name\":\"hit_summary.hit_detail.hits_summary_id\",\"type\":\"number\",\"count\":0,\"scripted\":false,\"searchable\":true,\"aggregatable\":true,\"readFromDocValues\":true},{\"name\":\"hit_summary.hit_detail.id\",\"type\":\"number\",\"count\":0,\"scripted\":false,\"searchable\":true,\"aggregatable\":true,\"readFromDocValues\":true},{\"name\":\"hit_summary.hit_detail.rule_id\",\"type\":\"number\",\"count\":0,\"scripted\":false,\"searchable\":true,\"aggregatable\":true,\"readFromDocValues\":true},{\"name\":\"hit_summary.hit_detail.title\",\"type\":\"string\",\"count\":0,\"scripted\":false,\"searchable\":true,\"aggregatable\":false,\"readFromDocValues\":false},{\"name\":\"hit_summary.hit_detail.title.keyword\",\"type\":\"string\",\"count\":0,\"scripted\":false,\"searchable\":true,\"aggregatable\":true,\"readFromDocValues\":true},{\"name\":\"hit_summary.hit_type\",\"type\":\"string\",\"count\":0,\"scripted\":false,\"searchable\":true,\"aggregatable\":false,\"readFromDocValues\":false},{\"name\":\"hit_summary.hit_type.keyword\",\"type\":\"string\",\"count\":0,\"scripted\":false,\"searchable\":true,\"aggregatable\":true,\"readFromDocValues\":true},{\"name\":\"hit_summary.id\",\"type\":\"number\",\"count\":0,\"scripted\":false,\"searchable\":true,\"aggregatable\":true,\"readFromDocValues\":true},{\"name\":\"hit_summary.passenger_id\",\"type\":\"number\",\"count\":0,\"scripted\":false,\"searchable\":true,\"aggregatable\":true,\"readFromDocValues\":true},{\"name\":\"hit_summary.rule_hit_count\",\"type\":\"number\",\"count\":0,\"scripted\":false,\"searchable\":true,\"aggregatable\":true,\"readFromDocValues\":true},{\"name\":\"hit_summary.wl_hit_count\",\"type\":\"number\",\"count\":0,\"scripted\":false,\"searchable\":true,\"aggregatable\":true,\"readFromDocValues\":true},{\"name\":\"id\",\"type\":\"number\",\"count\":0,\"scripted\":false,\"searchable\":true,\"aggregatable\":true,\"readFromDocValues\":true},{\"name\":\"lastName\",\"type\":\"string\",\"count\":0,\"scripted\":false,\"searchable\":true,\"aggregatable\":false,\"readFromDocValues\":false},{\"name\":\"lastName.keyword\",\"type\":\"string\",\"count\":0,\"scripted\":false,\"searchable\":true,\"aggregatable\":true,\"readFromDocValues\":true},{\"name\":\"lastname\",\"type\":\"string\",\"count\":0,\"scripted\":false,\"searchable\":true,\"aggregatable\":false,\"readFromDocValues\":false},{\"name\":\"lastname.keyword\",\"type\":\"string\",\"count\":0,\"scripted\":false,\"searchable\":true,\"aggregatable\":true,\"readFromDocValues\":true},{\"name\":\"passenger.age\",\"type\":\"number\",\"count\":0,\"scripted\":false,\"searchable\":true,\"aggregatable\":true,\"readFromDocValues\":true},{\"name\":\"passenger.citizenship_country\",\"type\":\"string\",\"count\":0,\"scripted\":false,\"searchable\":true,\"aggregatable\":false,\"readFromDocValues\":false},{\"name\":\"passenger.citizenship_country.keyword\",\"type\":\"string\",\"count\":0,\"scripted\":false,\"searchable\":true,\"aggregatable\":true,\"readFromDocValues\":true},{\"name\":\"passenger.days_visa_valid\",\"type\":\"number\",\"count\":0,\"scripted\":false,\"searchable\":true,\"aggregatable\":true,\"readFromDocValues\":true},{\"name\":\"passenger.debark_country\",\"type\":\"string\",\"count\":0,\"scripted\":false,\"searchable\":true,\"aggregatable\":false,\"readFromDocValues\":false},{\"name\":\"passenger.debark_country.keyword\",\"type\":\"string\",\"count\":0,\"scripted\":false,\"searchable\":true,\"aggregatable\":true,\"readFromDocValues\":true},{\"name\":\"passenger.debarkation\",\"type\":\"string\",\"count\":0,\"scripted\":false,\"searchable\":true,\"aggregatable\":false,\"readFromDocValues\":false},{\"name\":\"passenger.debarkation.keyword\",\"type\":\"string\",\"count\":0,\"scripted\":false,\"searchable\":true,\"aggregatable\":true,\"readFromDocValues\":true},{\"name\":\"passenger.debarkation_coordination\",\"type\":\"geo_point\",\"count\":0,\"scripted\":false,\"searchable\":true,\"aggregatable\":true,\"readFromDocValues\":true},{\"name\":\"passenger.dob\",\"type\":\"date\",\"count\":0,\"scripted\":false,\"searchable\":true,\"aggregatable\":true,\"readFromDocValues\":true},{\"name\":\"passenger.embark_country\",\"type\":\"string\",\"count\":0,\"scripted\":false,\"searchable\":true,\"aggregatable\":false,\"readFromDocValues\":false},{\"name\":\"passenger.embark_country.keyword\",\"type\":\"string\",\"count\":0,\"scripted\":false,\"searchable\":true,\"aggregatable\":true,\"readFromDocValues\":true},{\"name\":\"passenger.embarkation\",\"type\":\"string\",\"count\":0,\"scripted\":false,\"searchable\":true,\"aggregatable\":false,\"readFromDocValues\":false},{\"name\":\"passenger.embarkation.keyword\",\"type\":\"string\",\"count\":0,\"scripted\":false,\"searchable\":true,\"aggregatable\":true,\"readFromDocValues\":true},{\"name\":\"passenger.embarkation_coordination\",\"type\":\"geo_point\",\"count\":0,\"scripted\":false,\"searchable\":true,\"aggregatable\":true,\"readFromDocValues\":true},{\"name\":\"passenger.first_name\",\"type\":\"string\",\"count\":0,\"scripted\":false,\"searchable\":true,\"aggregatable\":false,\"readFromDocValues\":false},{\"name\":\"passenger.first_name.keyword\",\"type\":\"string\",\"count\":0,\"scripted\":false,\"searchable\":true,\"aggregatable\":true,\"readFromDocValues\":true},{\"name\":\"passenger.gender\",\"type\":\"string\",\"count\":0,\"scripted\":false,\"searchable\":true,\"aggregatable\":false,\"readFromDocValues\":false},{\"name\":\"passenger.gender.keyword\",\"type\":\"string\",\"count\":0,\"scripted\":false,\"searchable\":true,\"aggregatable\":true,\"readFromDocValues\":true},{\"name\":\"passenger.id\",\"type\":\"number\",\"count\":0,\"scripted\":false,\"searchable\":true,\"aggregatable\":true,\"readFromDocValues\":true},{\"name\":\"passenger.last_name\",\"type\":\"string\",\"count\":0,\"scripted\":false,\"searchable\":true,\"aggregatable\":false,\"readFromDocValues\":false},{\"name\":\"passenger.last_name.keyword\",\"type\":\"string\",\"count\":0,\"scripted\":false,\"searchable\":true,\"aggregatable\":true,\"readFromDocValues\":true},{\"name\":\"passenger.middle_name\",\"type\":\"string\",\"count\":0,\"scripted\":false,\"searchable\":true,\"aggregatable\":false,\"readFromDocValues\":false},{\"name\":\"passenger.middle_name.keyword\",\"type\":\"string\",\"count\":0,\"scripted\":false,\"searchable\":true,\"aggregatable\":true,\"readFromDocValues\":true},{\"name\":\"passenger.p_citizenship_country\",\"type\":\"string\",\"count\":0,\"scripted\":false,\"searchable\":true,\"aggregatable\":false,\"readFromDocValues\":false},{\"name\":\"passenger.p_citizenship_country.keyword\",\"type\":\"string\",\"count\":0,\"scripted\":false,\"searchable\":true,\"aggregatable\":true,\"readFromDocValues\":true},{\"name\":\"passenger.passenger_type\",\"type\":\"string\",\"count\":0,\"scripted\":false,\"searchable\":true,\"aggregatable\":false,\"readFromDocValues\":false},{\"name\":\"passenger.passenger_type.keyword\",\"type\":\"string\",\"count\":0,\"scripted\":false,\"searchable\":true,\"aggregatable\":true,\"readFromDocValues\":true},{\"name\":\"passenger.paxid\",\"type\":\"number\",\"count\":0,\"scripted\":false,\"searchable\":true,\"aggregatable\":true,\"readFromDocValues\":true},{\"name\":\"passenger.ref_number\",\"type\":\"string\",\"count\":0,\"scripted\":false,\"searchable\":true,\"aggregatable\":false,\"readFromDocValues\":false},{\"name\":\"passenger.ref_number.keyword\",\"type\":\"string\",\"count\":0,\"scripted\":false,\"searchable\":true,\"aggregatable\":true,\"readFromDocValues\":true},{\"name\":\"passenger.residency_country\",\"type\":\"string\",\"count\":0,\"scripted\":false,\"searchable\":true,\"aggregatable\":false,\"readFromDocValues\":false},{\"name\":\"passenger.residency_country.keyword\",\"type\":\"string\",\"count\":0,\"scripted\":false,\"searchable\":true,\"aggregatable\":true,\"readFromDocValues\":true},{\"name\":\"passenger.travel_frequency\",\"type\":\"number\",\"count\":0,\"scripted\":false,\"searchable\":true,\"aggregatable\":true,\"readFromDocValues\":true},{\"name\":\"passenger.watchlistCheckTimestamp\",\"type\":\"date\",\"count\":0,\"scripted\":false,\"searchable\":true,\"aggregatable\":true,\"readFromDocValues\":true},{\"name\":\"passenger.watchlistchecktimestamp\",\"type\":\"date\",\"count\":0,\"scripted\":false,\"searchable\":true,\"aggregatable\":true,\"readFromDocValues\":true},{\"name\":\"passengerName\",\"type\":\"string\",\"count\":0,\"scripted\":false,\"searchable\":true,\"aggregatable\":false,\"readFromDocValues\":false},{\"name\":\"passengerName.keyword\",\"type\":\"string\",\"count\":0,\"scripted\":false,\"searchable\":true,\"aggregatable\":true,\"readFromDocValues\":true},{\"name\":\"passengerType\",\"type\":\"string\",\"count\":0,\"scripted\":false,\"searchable\":true,\"aggregatable\":false,\"readFromDocValues\":false},{\"name\":\"passengerType.keyword\",\"type\":\"string\",\"count\":0,\"scripted\":false,\"searchable\":true,\"aggregatable\":true,\"readFromDocValues\":true},{\"name\":\"passengername\",\"type\":\"string\",\"count\":0,\"scripted\":false,\"searchable\":true,\"aggregatable\":false,\"readFromDocValues\":false},{\"name\":\"passengername.keyword\",\"type\":\"string\",\"count\":0,\"scripted\":false,\"searchable\":true,\"aggregatable\":true,\"readFromDocValues\":true},{\"name\":\"passengertype\",\"type\":\"string\",\"count\":0,\"scripted\":false,\"searchable\":true,\"aggregatable\":false,\"readFromDocValues\":false},{\"name\":\"passengertype.keyword\",\"type\":\"string\",\"count\":0,\"scripted\":false,\"searchable\":true,\"aggregatable\":true,\"readFromDocValues\":true},{\"name\":\"paxId\",\"type\":\"number\",\"count\":0,\"scripted\":false,\"searchable\":true,\"aggregatable\":true,\"readFromDocValues\":true},{\"name\":\"paxid\",\"type\":\"number\",\"count\":0,\"scripted\":false,\"searchable\":true,\"aggregatable\":true,\"readFromDocValues\":true},{\"name\":\"status\",\"type\":\"string\",\"count\":0,\"scripted\":false,\"searchable\":true,\"aggregatable\":false,\"readFromDocValues\":false},{\"name\":\"status.keyword\",\"type\":\"string\",\"count\":0,\"scripted\":false,\"searchable\":true,\"aggregatable\":true,\"readFromDocValues\":true},{\"name\":\"tags\",\"type\":\"string\",\"count\":0,\"scripted\":false,\"searchable\":true,\"aggregatable\":false,\"readFromDocValues\":false},{\"name\":\"tags.keyword\",\"type\":\"string\",\"count\":0,\"scripted\":false,\"searchable\":true,\"aggregatable\":true,\"readFromDocValues\":true},{\"name\":\"updated_at\",\"type\":\"date\",\"count\":0,\"scripted\":false,\"searchable\":true,\"aggregatable\":true,\"readFromDocValues\":true},{\"name\":\"updated_by\",\"type\":\"string\",\"count\":0,\"scripted\":false,\"searchable\":true,\"aggregatable\":false,\"readFromDocValues\":false},{\"name\":\"updated_by.keyword\",\"type\":\"string\",\"count\":0,\"scripted\":false,\"searchable\":true,\"aggregatable\":true,\"readFromDocValues\":true}]"
      },
      "migrationVersion": {
        "index-pattern": "6.5.0"
      }
    },
    {
      "id": "96df0890-2ba8-11e9-a5e4-2bbcf61c6cb1",
      "type": "index-pattern",
      "updated_at": "2019-02-21T21:39:01.546Z",
      "version": 18,
      "attributes": {
        "title": "flightpax*",
        "timeFieldName": "flightDate",
        "fields": "[{\"name\":\"@timestamp\",\"type\":\"date\",\"count\":0,\"scripted\":false,\"searchable\":true,\"aggregatable\":true,\"readFromDocValues\":true},{\"name\":\"@version\",\"type\":\"string\",\"count\":0,\"scripted\":false,\"searchable\":true,\"aggregatable\":false,\"readFromDocValues\":false},{\"name\":\"@version.keyword\",\"type\":\"string\",\"count\":0,\"scripted\":false,\"searchable\":true,\"aggregatable\":true,\"readFromDocValues\":true},{\"name\":\"_id\",\"type\":\"string\",\"count\":0,\"scripted\":false,\"searchable\":true,\"aggregatable\":true,\"readFromDocValues\":false},{\"name\":\"_index\",\"type\":\"string\",\"count\":0,\"scripted\":false,\"searchable\":true,\"aggregatable\":true,\"readFromDocValues\":false},{\"name\":\"_score\",\"type\":\"number\",\"count\":0,\"scripted\":false,\"searchable\":false,\"aggregatable\":false,\"readFromDocValues\":false},{\"name\":\"_source\",\"type\":\"_source\",\"count\":0,\"scripted\":false,\"searchable\":false,\"aggregatable\":false,\"readFromDocValues\":false},{\"name\":\"_type\",\"type\":\"string\",\"count\":0,\"scripted\":false,\"searchable\":true,\"aggregatable\":true,\"readFromDocValues\":false},{\"name\":\"addresses.city\",\"type\":\"string\",\"count\":0,\"scripted\":false,\"searchable\":true,\"aggregatable\":false,\"readFromDocValues\":false},{\"name\":\"addresses.city.keyword\",\"type\":\"string\",\"count\":0,\"scripted\":false,\"searchable\":true,\"aggregatable\":true,\"readFromDocValues\":true},{\"name\":\"addresses.country\",\"type\":\"string\",\"count\":0,\"scripted\":false,\"searchable\":true,\"aggregatable\":false,\"readFromDocValues\":false},{\"name\":\"addresses.country.keyword\",\"type\":\"string\",\"count\":0,\"scripted\":false,\"searchable\":true,\"aggregatable\":true,\"readFromDocValues\":true},{\"name\":\"addresses.createdAt\",\"type\":\"date\",\"count\":0,\"scripted\":false,\"searchable\":true,\"aggregatable\":true,\"readFromDocValues\":true},{\"name\":\"addresses.createdBy\",\"type\":\"string\",\"count\":0,\"scripted\":false,\"searchable\":true,\"aggregatable\":false,\"readFromDocValues\":false},{\"name\":\"addresses.createdBy.keyword\",\"type\":\"string\",\"count\":0,\"scripted\":false,\"searchable\":true,\"aggregatable\":true,\"readFromDocValues\":true},{\"name\":\"addresses.id\",\"type\":\"number\",\"count\":0,\"scripted\":false,\"searchable\":true,\"aggregatable\":true,\"readFromDocValues\":true},{\"name\":\"addresses.line1\",\"type\":\"string\",\"count\":0,\"scripted\":false,\"searchable\":true,\"aggregatable\":false,\"readFromDocValues\":false},{\"name\":\"addresses.line1.keyword\",\"type\":\"string\",\"count\":0,\"scripted\":false,\"searchable\":true,\"aggregatable\":true,\"readFromDocValues\":true},{\"name\":\"addresses.postalCode\",\"type\":\"string\",\"count\":0,\"scripted\":false,\"searchable\":true,\"aggregatable\":false,\"readFromDocValues\":false},{\"name\":\"addresses.postalCode.keyword\",\"type\":\"string\",\"count\":0,\"scripted\":false,\"searchable\":true,\"aggregatable\":true,\"readFromDocValues\":true},{\"name\":\"addresses.state\",\"type\":\"string\",\"count\":0,\"scripted\":false,\"searchable\":true,\"aggregatable\":false,\"readFromDocValues\":false},{\"name\":\"addresses.state.keyword\",\"type\":\"string\",\"count\":0,\"scripted\":false,\"searchable\":true,\"aggregatable\":true,\"readFromDocValues\":true},{\"name\":\"apis\",\"type\":\"string\",\"count\":0,\"scripted\":false,\"searchable\":true,\"aggregatable\":false,\"readFromDocValues\":false},{\"name\":\"apis.keyword\",\"type\":\"string\",\"count\":0,\"scripted\":false,\"searchable\":true,\"aggregatable\":true,\"readFromDocValues\":true},{\"name\":\"carrier\",\"type\":\"string\",\"count\":0,\"scripted\":false,\"searchable\":true,\"aggregatable\":false,\"readFromDocValues\":false},{\"name\":\"carrier.keyword\",\"type\":\"string\",\"count\":0,\"scripted\":false,\"searchable\":true,\"aggregatable\":true,\"readFromDocValues\":true},{\"name\":\"citizenshipCountry\",\"type\":\"string\",\"count\":0,\"scripted\":false,\"searchable\":true,\"aggregatable\":false,\"readFromDocValues\":false},{\"name\":\"citizenshipCountry.keyword\",\"type\":\"string\",\"count\":0,\"scripted\":false,\"searchable\":true,\"aggregatable\":true,\"readFromDocValues\":true},{\"name\":\"debarkation\",\"type\":\"string\",\"count\":0,\"scripted\":false,\"searchable\":true,\"aggregatable\":false,\"readFromDocValues\":false},{\"name\":\"debarkation.keyword\",\"type\":\"string\",\"count\":0,\"scripted\":false,\"searchable\":true,\"aggregatable\":true,\"readFromDocValues\":true},{\"name\":\"destination\",\"type\":\"string\",\"count\":0,\"scripted\":false,\"searchable\":true,\"aggregatable\":false,\"readFromDocValues\":false},{\"name\":\"destination.keyword\",\"type\":\"string\",\"count\":0,\"scripted\":false,\"searchable\":true,\"aggregatable\":true,\"readFromDocValues\":true},{\"name\":\"direction\",\"type\":\"string\",\"count\":0,\"scripted\":false,\"searchable\":true,\"aggregatable\":false,\"readFromDocValues\":false},{\"name\":\"direction.keyword\",\"type\":\"string\",\"count\":0,\"scripted\":false,\"searchable\":true,\"aggregatable\":true,\"readFromDocValues\":true},{\"name\":\"dob\",\"type\":\"date\",\"count\":0,\"scripted\":false,\"searchable\":true,\"aggregatable\":true,\"readFromDocValues\":true},{\"name\":\"documents.documentNumber\",\"type\":\"string\",\"count\":0,\"scripted\":false,\"searchable\":true,\"aggregatable\":false,\"readFromDocValues\":false},{\"name\":\"documents.documentNumber.keyword\",\"type\":\"string\",\"count\":0,\"scripted\":false,\"searchable\":true,\"aggregatable\":true,\"readFromDocValues\":true},{\"name\":\"documents.documentType\",\"type\":\"string\",\"count\":0,\"scripted\":false,\"searchable\":true,\"aggregatable\":false,\"readFromDocValues\":false},{\"name\":\"documents.documentType.keyword\",\"type\":\"string\",\"count\":0,\"scripted\":false,\"searchable\":true,\"aggregatable\":true,\"readFromDocValues\":true},{\"name\":\"documents.expirationDate\",\"type\":\"date\",\"count\":0,\"scripted\":false,\"searchable\":true,\"aggregatable\":true,\"readFromDocValues\":true},{\"name\":\"documents.firstName\",\"type\":\"string\",\"count\":0,\"scripted\":false,\"searchable\":true,\"aggregatable\":false,\"readFromDocValues\":false},{\"name\":\"documents.firstName.keyword\",\"type\":\"string\",\"count\":0,\"scripted\":false,\"searchable\":true,\"aggregatable\":true,\"readFromDocValues\":true},{\"name\":\"documents.id\",\"type\":\"number\",\"count\":0,\"scripted\":false,\"searchable\":true,\"aggregatable\":true,\"readFromDocValues\":true},{\"name\":\"documents.issuanceCountry\",\"type\":\"string\",\"count\":0,\"scripted\":false,\"searchable\":true,\"aggregatable\":false,\"readFromDocValues\":false},{\"name\":\"documents.issuanceCountry.keyword\",\"type\":\"string\",\"count\":0,\"scripted\":false,\"searchable\":true,\"aggregatable\":true,\"readFromDocValues\":true},{\"name\":\"documents.issuanceDate\",\"type\":\"date\",\"count\":0,\"scripted\":false,\"searchable\":true,\"aggregatable\":true,\"readFromDocValues\":true},{\"name\":\"documents.lastName\",\"type\":\"string\",\"count\":0,\"scripted\":false,\"searchable\":true,\"aggregatable\":false,\"readFromDocValues\":false},{\"name\":\"documents.lastName.keyword\",\"type\":\"string\",\"count\":0,\"scripted\":false,\"searchable\":true,\"aggregatable\":true,\"readFromDocValues\":true},{\"name\":\"embarkation\",\"type\":\"string\",\"count\":0,\"scripted\":false,\"searchable\":true,\"aggregatable\":false,\"readFromDocValues\":false},{\"name\":\"embarkation.keyword\",\"type\":\"string\",\"count\":0,\"scripted\":false,\"searchable\":true,\"aggregatable\":true,\"readFromDocValues\":true},{\"name\":\"eta\",\"type\":\"date\",\"count\":0,\"scripted\":false,\"searchable\":true,\"aggregatable\":true,\"readFromDocValues\":true},{\"name\":\"etd\",\"type\":\"date\",\"count\":0,\"scripted\":false,\"searchable\":true,\"aggregatable\":true,\"readFromDocValues\":true},{\"name\":\"firstName\",\"type\":\"string\",\"count\":0,\"scripted\":false,\"searchable\":true,\"aggregatable\":false,\"readFromDocValues\":false},{\"name\":\"firstName.keyword\",\"type\":\"string\",\"count\":0,\"scripted\":false,\"searchable\":true,\"aggregatable\":true,\"readFromDocValues\":true},{\"name\":\"flightDate\",\"type\":\"date\",\"count\":0,\"scripted\":false,\"searchable\":true,\"aggregatable\":true,\"readFromDocValues\":true},{\"name\":\"flightId\",\"type\":\"number\",\"count\":0,\"scripted\":false,\"searchable\":true,\"aggregatable\":true,\"readFromDocValues\":true},{\"name\":\"flightNumber\",\"type\":\"string\",\"count\":0,\"scripted\":false,\"searchable\":true,\"aggregatable\":false,\"readFromDocValues\":false},{\"name\":\"flightNumber.keyword\",\"type\":\"string\",\"count\":0,\"scripted\":false,\"searchable\":true,\"aggregatable\":true,\"readFromDocValues\":true},{\"name\":\"gender\",\"type\":\"string\",\"count\":0,\"scripted\":false,\"searchable\":true,\"aggregatable\":false,\"readFromDocValues\":false},{\"name\":\"gender.keyword\",\"type\":\"string\",\"count\":0,\"scripted\":false,\"searchable\":true,\"aggregatable\":true,\"readFromDocValues\":true},{\"name\":\"id\",\"type\":\"string\",\"count\":0,\"scripted\":false,\"searchable\":true,\"aggregatable\":false,\"readFromDocValues\":false},{\"name\":\"id.keyword\",\"type\":\"string\",\"count\":0,\"scripted\":false,\"searchable\":true,\"aggregatable\":true,\"readFromDocValues\":true},{\"name\":\"lastName\",\"type\":\"string\",\"count\":0,\"scripted\":false,\"searchable\":true,\"aggregatable\":false,\"readFromDocValues\":false},{\"name\":\"lastName.keyword\",\"type\":\"string\",\"count\":0,\"scripted\":false,\"searchable\":true,\"aggregatable\":true,\"readFromDocValues\":true},{\"name\":\"middleName\",\"type\":\"string\",\"count\":0,\"scripted\":false,\"searchable\":true,\"aggregatable\":false,\"readFromDocValues\":false},{\"name\":\"middleName.keyword\",\"type\":\"string\",\"count\":0,\"scripted\":false,\"searchable\":true,\"aggregatable\":true,\"readFromDocValues\":true},{\"name\":\"origin\",\"type\":\"string\",\"count\":0,\"scripted\":false,\"searchable\":true,\"aggregatable\":false,\"readFromDocValues\":false},{\"name\":\"origin.keyword\",\"type\":\"string\",\"count\":0,\"scripted\":false,\"searchable\":true,\"aggregatable\":true,\"readFromDocValues\":true},{\"name\":\"passengerId\",\"type\":\"number\",\"count\":0,\"scripted\":false,\"searchable\":true,\"aggregatable\":true,\"readFromDocValues\":true},{\"name\":\"passengerType\",\"type\":\"string\",\"count\":0,\"scripted\":false,\"searchable\":true,\"aggregatable\":false,\"readFromDocValues\":false},{\"name\":\"passengerType.keyword\",\"type\":\"string\",\"count\":0,\"scripted\":false,\"searchable\":true,\"aggregatable\":true,\"readFromDocValues\":true},{\"name\":\"pnr\",\"type\":\"string\",\"count\":0,\"scripted\":false,\"searchable\":true,\"aggregatable\":false,\"readFromDocValues\":false},{\"name\":\"pnr.keyword\",\"type\":\"string\",\"count\":0,\"scripted\":false,\"searchable\":true,\"aggregatable\":true,\"readFromDocValues\":true},{\"name\":\"residencyCountry\",\"type\":\"string\",\"count\":0,\"scripted\":false,\"searchable\":true,\"aggregatable\":false,\"readFromDocValues\":false},{\"name\":\"residencyCountry.keyword\",\"type\":\"string\",\"count\":0,\"scripted\":false,\"searchable\":true,\"aggregatable\":true,\"readFromDocValues\":true},{\"name\":\"seatNumber\",\"type\":\"string\",\"count\":0,\"scripted\":false,\"searchable\":true,\"aggregatable\":false,\"readFromDocValues\":false},{\"name\":\"seatNumber.keyword\",\"type\":\"string\",\"count\":0,\"scripted\":false,\"searchable\":true,\"aggregatable\":true,\"readFromDocValues\":true},{\"name\":\"tags\",\"type\":\"string\",\"count\":0,\"scripted\":false,\"searchable\":true,\"aggregatable\":false,\"readFromDocValues\":false},{\"name\":\"tags.keyword\",\"type\":\"string\",\"count\":0,\"scripted\":false,\"searchable\":true,\"aggregatable\":true,\"readFromDocValues\":true},{\"name\":\"watchlist_match.id\",\"type\":\"number\",\"count\":0,\"scripted\":false,\"searchable\":true,\"aggregatable\":true,\"readFromDocValues\":true},{\"name\":\"watchlist_match.last_run_timestamp\",\"type\":\"date\",\"count\":0,\"scripted\":false,\"searchable\":true,\"aggregatable\":true,\"readFromDocValues\":true},{\"name\":\"watchlist_match.passenger_id\",\"type\":\"number\",\"count\":0,\"scripted\":false,\"searchable\":true,\"aggregatable\":true,\"readFromDocValues\":true},{\"name\":\"watchlist_match.percent_match\",\"type\":\"number\",\"count\":0,\"scripted\":false,\"searchable\":true,\"aggregatable\":true,\"readFromDocValues\":true},{\"name\":\"watchlist_match.verified_status\",\"type\":\"number\",\"count\":0,\"scripted\":false,\"searchable\":true,\"aggregatable\":true,\"readFromDocValues\":true},{\"name\":\"watchlist_match.watchlist_item_id\",\"type\":\"number\",\"count\":0,\"scripted\":false,\"searchable\":true,\"aggregatable\":true,\"readFromDocValues\":true}]"
      },
      "migrationVersion": {
        "index-pattern": "6.5.0"
      }
    },
    {
      "id": "7cfbbdc0-2e13-11e9-81a3-0f5bd8b0a7ac",
      "type": "dashboard",
      "updated_at": "2019-03-14T18:10:50.414Z",
      "version": 1,
      "attributes": {
        "title": "Demo Dashboard 20190301",
        "hits": 0,
        "description": "This is the default dashboard.",
        "panelsJSON": "[{\"embeddableConfig\":{\"mapCenter\":[40.48038142908172,-21.796875000000004],\"mapZoom\":3},\"gridData\":{\"x\":0,\"y\":11,\"w\":30,\"h\":21,\"i\":\"1\"},\"id\":\"2cf5c260-2ce4-11e9-81a3-0f5bd8b0a7ac\",\"panelIndex\":\"1\",\"type\":\"visualization\",\"version\":\"6.5.0\"},{\"embeddableConfig\":{},\"gridData\":{\"x\":30,\"y\":20,\"w\":5,\"h\":6,\"i\":\"2\"},\"id\":\"20062130-2ee2-11e9-b8b9-8b6cf228ac97\",\"panelIndex\":\"2\",\"title\":\"Inbound Flights\",\"type\":\"visualization\",\"version\":\"6.5.0\"},{\"embeddableConfig\":{},\"gridData\":{\"x\":30,\"y\":26,\"w\":5,\"h\":6,\"i\":\"3\"},\"id\":\"8e6b8b10-2ee2-11e9-b8b9-8b6cf228ac97\",\"panelIndex\":\"3\",\"title\":\"Outbound Flights\",\"type\":\"visualization\",\"version\":\"6.5.0\"},{\"embeddableConfig\":{},\"gridData\":{\"x\":35,\"y\":26,\"w\":7,\"h\":6,\"i\":\"4\"},\"id\":\"881e1000-2ee9-11e9-b8b9-8b6cf228ac97\",\"panelIndex\":\"4\",\"title\":\"Outbound Passengers\",\"type\":\"visualization\",\"version\":\"6.5.0\"},{\"embeddableConfig\":{},\"gridData\":{\"x\":35,\"y\":20,\"w\":7,\"h\":6,\"i\":\"5\"},\"id\":\"846e0ae0-2eea-11e9-b8b9-8b6cf228ac97\",\"panelIndex\":\"5\",\"title\":\"Inbound Passengers\",\"type\":\"visualization\",\"version\":\"6.5.0\"},{\"embeddableConfig\":{},\"gridData\":{\"x\":30,\"y\":11,\"w\":18,\"h\":9,\"i\":\"6\"},\"id\":\"cd0264d0-3094-11e9-b8b9-8b6cf228ac97\",\"panelIndex\":\"6\",\"type\":\"visualization\",\"version\":\"6.5.0\"},{\"embeddableConfig\":{},\"gridData\":{\"x\":0,\"y\":0,\"w\":48,\"h\":11,\"i\":\"7\"},\"id\":\"08af9740-3a0a-11e9-95bb-75d44e71a49d\",\"panelIndex\":\"7\",\"type\":\"visualization\",\"version\":\"6.5.0\"},{\"embeddableConfig\":{},\"gridData\":{\"x\":0,\"y\":32,\"w\":24,\"h\":11,\"i\":\"9\"},\"id\":\"938c2f80-3a0b-11e9-95bb-75d44e71a49d\",\"panelIndex\":\"9\",\"type\":\"visualization\",\"version\":\"6.5.0\"}]",
        "optionsJSON": "{\"darkTheme\":false,\"hidePanelTitles\":false,\"useMargins\":true}",
        "version": 1,
        "timeRestore": false,
        "kibanaSavedObjectMeta": {
          "searchSourceJSON": "{\"query\":{\"language\":\"kuery\",\"query\":\"\"},\"filter\":[]}"
        }
      }
    }
  ]
}